drycli/__init__.py
drycli/_version.py
drycli/py.typed
drycli-0.0.3.dist-info/licenses/LICENSE
drycli-0.0.3.dist-info/METADATA
drycli-0.0.3.dist-info/WHEEL
drycli-0.0.3.dist-info/top_level.txt
drycli-0.0.3.dist-info/RECORD
